[{"id":"1","nombre":"Edouard","notificationToken":null},{"id":"2","nombre":"Thia","notificationToken":null},{"id":"3","nombre":"Yalonda","notificationToken":null},{"id":"4","nombre":"Elysha","notificationToken":null},{"id":"5","nombre":"Kaja","notificationToken":null},{"id":"6","nombre":"Romain","notificationToken":null},{"id":"7","nombre":"Alysia","notificationToken":null},{"id":"8","nombre":"Jean","notificationToken":null},{"id":"9","nombre":"Roland","notificationToken":null},{"id":"10","nombre":"Dane","notificationToken":null},{"id":"11","nombre":"Albina","notificationToken":null},{"id":"12","nombre":"Dodie","notificationToken":null},{"id":"13","nombre":"Alfi","notificationToken":null},{"id":"14","nombre":"Myrwyn","notificationToken":null},{"id":"15","nombre":"Trev","notificationToken":null},{"id":"16","nombre":"Gracia","notificationToken":null},{"id":"17","nombre":"Emalee","notificationToken":null},{"id":"18","nombre":"Rhianon","notificationToken":null},{"id":"19","nombre":"Boonie","notificationToken":null},{"id":"20","nombre":"Arleta","notificationToken":null},{"id":"EgesOrh9H1QMdhcFCmpD5VrM0ku2","nombre":"Cristian Soria","notificationToken":"fBW99MxHSbSYa85hwPBULH:APA91bF7mSSHgbod65pExBVMXCZ7CtVpePVuXMvAaeJMyr2NiEAH8wYm8OCINvvXQHIqWyiHCUth_OvRMEPhEjkETzGO-2yCKfIAzOIaLy6iTNcKZLBNidTtSEb16OYMGexb8sgvULJr"}]